README.md
setup.cfg
setup.py
images/__init__.py
images/utils.py
utp.egg-info/PKG-INFO
utp.egg-info/SOURCES.txt
utp.egg-info/dependency_links.txt
utp.egg-info/requires.txt
utp.egg-info/top_level.txt