Metadata-Version: 1.1
Name: utp
Version: 0.2
Summary: helper functions for typical python problems
Home-page: https://github.com/user/reponame
Author: Patryk Seweryn
Author-email: patryk.seweryn@gmail.com
License: MIT
Download-URL: https://github.com/p-severin/utp/archive/v_0.1.tar.gz
Keywords: images,preprocessing,python
Platform: UNKNOWN
Classifier: Development Status :: 3 - Alpha
Classifier: Intended Audience :: Developers
Classifier: Topic :: Software Development :: Build Tools
Classifier: License :: OSI Approved :: MIT License
Classifier: Programming Language :: Python :: 3
Classifier: Programming Language :: Python :: 3.4
Classifier: Programming Language :: Python :: 3.5
Classifier: Programming Language :: Python :: 3.6
